example_pkg/__init__.py
packaging_tutorial_ramon-0.0.1.dist-info/LICENSE
packaging_tutorial_ramon-0.0.1.dist-info/METADATA
packaging_tutorial_ramon-0.0.1.dist-info/WHEEL
packaging_tutorial_ramon-0.0.1.dist-info/top_level.txt
packaging_tutorial_ramon-0.0.1.dist-info/RECORD
