Metadata-Version: 2.1
Name: packaging-tutorial-ramon
Version: 0.0.1
Summary: Purly testing packaging.
Home-page: http://ramon.wang
Author: ramon
Author-email: ramon_wang@hotmail.com
License: MIT License
Platform: UNKNOWN
